math_kel/__init__.py
math_kel/__main__.py
math_kel/server.py
mcp_math-0.1.1.dist-info/METADATA
mcp_math-0.1.1.dist-info/WHEEL
mcp_math-0.1.1.dist-info/entry_points.txt
mcp_math-0.1.1.dist-info/top_level.txt
mcp_math-0.1.1.dist-info/RECORD
