Metadata-Version: 2.4
Name: mcp-math
Version: 0.1.1
Summary: One MCP Base Math Func
Requires-Python: >=3.11
Requires-Dist: build>=1.2.2.post1
Requires-Dist: mcp>=1.9.4
Requires-Dist: twine>=6.1.0
